odoo/addons/dbfilter_from_header/README.rst
odoo/addons/dbfilter_from_header/__init__.py
odoo/addons/dbfilter_from_header/__manifest__.py
odoo/addons/dbfilter_from_header/override.py
odoo/addons/dbfilter_from_header/i18n/dbfilter_from_header.pot
odoo/addons/dbfilter_from_header/i18n/zh_CN.po
odoo/addons/dbfilter_from_header/readme/CONFIGURE.rst
odoo/addons/dbfilter_from_header/readme/CONTRIBUTORS.rst
odoo/addons/dbfilter_from_header/readme/DESCRIPTION.rst
odoo/addons/dbfilter_from_header/readme/INSTALL.rst
odoo/addons/dbfilter_from_header/readme/USAGE.rst
odoo/addons/dbfilter_from_header/static/description/icon.png
odoo/addons/dbfilter_from_header/static/description/index.html
odoo12_addon_dbfilter_from_header-12.0.1.0.2.dist-info/METADATA
odoo12_addon_dbfilter_from_header-12.0.1.0.2.dist-info/WHEEL
odoo12_addon_dbfilter_from_header-12.0.1.0.2.dist-info/top_level.txt
odoo12_addon_dbfilter_from_header-12.0.1.0.2.dist-info/RECORD
